spbdl
