Metadata-Version: 2.1
Name: spbdl
Version: 1.1.2
Summary: Download images from shitpostbot database
Home-page: https://github.com/Boidushya/spbdl
Author: Boidushya Bhattacharya
Author-email: boidushyabhattacharya@gmail.com
License: MIT
Download-URL: https://github.com/Boidushya/spbdl/archive/v_01.tar.gz
Keywords: shitpostbot,spb,spbdl
Platform: UNKNOWN
Classifier: Development Status :: 4 - Beta
Classifier: Intended Audience :: Developers
Classifier: Topic :: Software Development :: Build Tools
Classifier: License :: OSI Approved :: MIT License
Classifier: Programming Language :: Python :: 3.6
Classifier: Programming Language :: Python :: 3.7
Classifier: Programming Language :: Python :: 3.8
